.bumpversion.cfg
.gitignore
DEVELOP.rst
LICENSE.txt
MANIFEST.in
Makefile
README.rst
TUTORIAL.rst
setup.cfg
setup.py
.circleci/config.yml
src/ninvoice2data/__init__.py
src/ninvoice2data/main.py
src/ninvoice2data.egg-info/PKG-INFO
src/ninvoice2data.egg-info/SOURCES.txt
src/ninvoice2data.egg-info/dependency_links.txt
src/ninvoice2data.egg-info/entry_points.txt
src/ninvoice2data.egg-info/requires.txt
src/ninvoice2data.egg-info/top_level.txt
src/ninvoice2data/extract/__init__.py
src/ninvoice2data/extract/invoice_template.py
src/ninvoice2data/extract/loader.py
src/ninvoice2data/extract/plugins/__init__.py
src/ninvoice2data/extract/plugins/__interface__.py
src/ninvoice2data/extract/plugins/lines.py
src/ninvoice2data/extract/plugins/tables.py
src/ninvoice2data/extract/templates/be/be.boucherie.pochet.yml
src/ninvoice2data/extract/templates/be/be.cebeo.yml
src/ninvoice2data/extract/templates/be/be.melchior-vins.yml
src/ninvoice2data/extract/templates/be/be.proximus.yml
src/ninvoice2data/extract/templates/be/be.securex.social.yml
src/ninvoice2data/extract/templates/ch/ch.pcengines.yml
src/ninvoice2data/extract/templates/com/com.amazon.aws.yml
src/ninvoice2data/extract/templates/com/com.apps4rent.yml
src/ninvoice2data/extract/templates/com/com.binarylife.yml
src/ninvoice2data/extract/templates/com/com.bloomberg.yml
src/ninvoice2data/extract/templates/com/com.cloudns.yml
src/ninvoice2data/extract/templates/com/com.datadoghq.yml
src/ninvoice2data/extract/templates/com/com.digitalocean.yml
src/ninvoice2data/extract/templates/com/com.envato.yml
src/ninvoice2data/extract/templates/com/com.expressvpn.yml
src/ninvoice2data/extract/templates/com/com.flipkart.WSRetail.yml
src/ninvoice2data/extract/templates/com/com.ftserussell.yml
src/ninvoice2data/extract/templates/com/com.github.yml
src/ninvoice2data/extract/templates/com/com.globalsign.yml
src/ninvoice2data/extract/templates/com/com.google.adwords.hk.yml
src/ninvoice2data/extract/templates/com/com.hobohost.yml
src/ninvoice2data/extract/templates/com/com.linode.yml
src/ninvoice2data/extract/templates/com/com.microsoftonline.hk-v2017.yml
src/ninvoice2data/extract/templates/com/com.microsoftonline.hk.yml
src/ninvoice2data/extract/templates/com/com.namecheap.yml
