Metadata-Version: 2.1
Name: ninvoice2data
Version: 0.4.14
Summary: Python parser to extract data from pdf invoice
Home-page: https://github.com/invoice-x/ninvoice2data
Author: Manuel Riel
License: UNKNOWN
Keywords: pdf,invoicing
Platform: UNKNOWN
Classifier: Development Status :: 4 - Beta
Classifier: Environment :: MacOS X
Classifier: Environment :: Console
Classifier: Environment :: Win32 (MS Windows)
Classifier: Operating System :: MacOS
Classifier: Operating System :: POSIX
Classifier: Operating System :: Unix
Classifier: Operating System :: Microsoft :: Windows
Classifier: License :: OSI Approved :: MIT License
Classifier: Programming Language :: Python :: 2.7
Classifier: Programming Language :: Python :: 3.6
Classifier: Programming Language :: Python :: 3.7
Classifier: Topic :: Office/Business :: Financial
Classifier: Topic :: Office/Business :: Financial :: Accounting
